omnihuman/__init__.py
omnihuman/models/__init__.py
omnihuman/utils/__init__.py
omnihuman/utils/io.py
omnihuman-0.1.1.dist-info/LICENSE
omnihuman-0.1.1.dist-info/METADATA
omnihuman-0.1.1.dist-info/WHEEL
omnihuman-0.1.1.dist-info/RECORD
