Metadata-Version: 2.1
Name: omnihuman
Version: 0.1.1
Summary: AI model that understands text and humanoids.
Home-page: https://github.com/mdsrqbl/omnihuman.git
License: Apache 2.0
Keywords: ai,nlp,text,humanoids,pose,computer-vision
Author: Mudassar Iqbal
Author-email: mdsriqb@gmail.com
Requires-Python: >=3.8,<3.13
Classifier: License :: Other/Proprietary License
Classifier: Programming Language :: Python :: 3
Classifier: Programming Language :: Python :: 3.8
Classifier: Programming Language :: Python :: 3.9
Classifier: Programming Language :: Python :: 3.10
Classifier: Programming Language :: Python :: 3.11
Classifier: Programming Language :: Python :: 3.12
Requires-Dist: numpy (<2)
Requires-Dist: torch (>=2.2.2,<3.0.0)
Requires-Dist: torchvision (>=0.17.2,<0.18.0) ; python_version < "3.12"
Requires-Dist: torchvision (>=0.18) ; python_version >= "3.12"
Project-URL: Documentation, https://omnihuman.readthedocs.io/
Project-URL: Repository, https://github.com/mdsrqbl/omnihuman.git
